labels2tables/__init__.py
labels2tables/core.py
labels2tables/table.py
labels2tables/tags2table.py
labels2tables/uniquebool.py
labels2tables-0.1.0.dist-info/DESCRIPTION.rst
labels2tables-0.1.0.dist-info/METADATA
labels2tables-0.1.0.dist-info/RECORD
labels2tables-0.1.0.dist-info/WHEEL
labels2tables-0.1.0.dist-info/metadata.json
labels2tables-0.1.0.dist-info/top_level.txt
