Metadata-Version: 2.0
Name: labels2tables
Version: 0.1.0
Summary: Turns bibtex keywords into an academic summary table
Home-page: https://github.com/anjsimmo/labels2tables
Author: Andrew Simmons
Author-email: anjsimmo@gmail.com
License: MIT
Platform: UNKNOWN
Classifier: Development Status :: 3 - Alpha
Classifier: Intended Audience :: Science/Research
Classifier: License :: OSI Approved :: MIT License
Classifier: Topic :: Text Processing :: Markup
Classifier: Programming Language :: Python :: 2
Classifier: Programming Language :: Python :: 3
Requires-Dist: bibtexparser
Requires-Dist: enum34
